manage.py
karpyncho/reload_urls/__init__.py
tests/__init__.py
tests/another_urls.py
tests/settings.py
tests/test_init.py
tests/urls.py
karpyncho_reload_urls-0.1.1.dist-info/LICENSE
karpyncho_reload_urls-0.1.1.dist-info/METADATA
karpyncho_reload_urls-0.1.1.dist-info/WHEEL
karpyncho_reload_urls-0.1.1.dist-info/top_level.txt
karpyncho_reload_urls-0.1.1.dist-info/RECORD
