Metadata-Version: 2.1
Name: karpyncho-reload-urls
Version: 0.1.1
Summary: A context manaager to reload urls routing in unittests changing a django setting.
Author-email: Sebastian Quiles <qsebas@gmail.com>
Project-URL: homepage, https://github.com/karpyncho/reload-urls
Project-URL: repository, https://github.com/karpyncho/reload-urls
Project-URL: changelog, https://github.com/karpyncho/reload-urls/blob/main/CHANGELOG.md
Classifier: Development Status :: 3 - Alpha
Classifier: License :: OSI Approved :: MIT License
Classifier: Natural Language :: English
Classifier: Operating System :: OS Independent
Classifier: Programming Language :: Python
Classifier: Programming Language :: Python :: 3.7
Classifier: Programming Language :: Python :: 3.8
Classifier: Programming Language :: Python :: 3.9
Classifier: Programming Language :: Python :: 3.10
Classifier: Programming Language :: Python :: 3.11
Requires-Python: >=3.7
License-File: LICENSE
Requires-Dist: django (>=2.2)
Provides-Extra: dev
Requires-Dist: tox ; extra == 'dev'
Requires-Dist: build ; extra == 'dev'
Requires-Dist: flake8 ; extra == 'dev'
Requires-Dist: flake8-import-order ; extra == 'dev'
Requires-Dist: pep8-naming ; extra == 'dev'
Requires-Dist: flake8-colors ; extra == 'dev'
Requires-Dist: pylint ; extra == 'dev'
Requires-Dist: bandit ; extra == 'dev'
Requires-Dist: pytest ; extra == 'dev'
Requires-Dist: coverage ; extra == 'dev'
Requires-Dist: pytest-cov ; extra == 'dev'
